docsmith.py
llm_docsmith-0.3.1.dist-info/licenses/LICENSE
llm_docsmith-0.3.1.dist-info/METADATA
llm_docsmith-0.3.1.dist-info/WHEEL
llm_docsmith-0.3.1.dist-info/entry_points.txt
llm_docsmith-0.3.1.dist-info/top_level.txt
llm_docsmith-0.3.1.dist-info/RECORD
