Metadata-Version: 2.4
Name: llm-docsmith
Version: 0.3.1
Summary: Generate Python docstrings automatically with LLM and syntax trees.
Author: Matheus Pedroni
Project-URL: Homepage, https://github.com/mathpn/llm-docsmith
Project-URL: Changelog, https://github.com/mathpn/llm-docsmith/releases
Project-URL: Issues, https://github.com/mathpn/llm-docsmith/issues
Classifier: Programming Language :: Python :: 3
Classifier: Operating System :: OS Independent
Requires-Python: >=3.12
License-File: LICENSE
Requires-Dist: libcst>=1.7.0
Requires-Dist: llm>=0.23
Requires-Dist: pydantic>=2.10.6
Provides-Extra: test
Requires-Dist: pytest; extra == "test"
Dynamic: license-file
